Design/ks_vandana_fp_div.v
module ks_vandana_fp_div(
	a1,
	b1,
	c,
	clk
);
	input wire [31:0] a1;
	input wire [31:0] b1;
	input wire clk;
	output reg [31:0] c;
	reg [31:0] a;
	reg [31:0] b;
	reg sa;
	reg sb;
	reg sc;
	reg [7:0] ea;
	reg [7:0] eb;
	reg [7:0] ec;
	reg [23:0] ma;
	reg [23:0] mb;
	reg [23:0] mc;
	reg [49:0] rq;
	always @(posedge clk) begin
		a <= a1;
		b <= b1;
		c[31] <= sc;
		c[30:23] <= ec;
		c[22:0] <= mc[22:0];
	end
	always @(*) begin : sv2v_autoblock_1
		reg [0:1] _sv2v_jump;
		_sv2v_jump = 2'b00;
		sa = a[31];
		sb = b[31];
		sc = sa ^ sb;
		ea = a[30:23];
		eb = b[30:23];
		ec = (ea - eb) + 8'b01111111;
		ma = 24'b000000000000000000000000 + a[22:0];
		mb = 24'b000000000000000000000000 + b[22:0];
		mc = 24'b000000000000000000000000;
		rq = 50'b00000000000000000000000000000000000000000000000000;
		ma[23] = 1;
		mb[23] = 1;
		rq[46:23] = ma[23:0];
		begin : sv2v_autoblock_2
			reg signed [31:0] t;
			for (t = 0; t < 24; t = t + 1)
				begin
					rq = rq << 1;
					rq[49] = 0;
					rq[49:24] = rq[49:24] - mb[23:0];
					if (rq[49] == 1)
						rq[49:24] = rq[49:24] + mb[23:0];
					else
						rq[0] = 1;
				end
		end
		mc = rq[23:0];
		begin : sv2v_autoblock_3
			reg signed [31:0] l;
			begin : sv2v_autoblock_4
				reg signed [31:0] _sv2v_value_on_break;
				for (l = 0; l < 25; l = l + 1)
					if (_sv2v_jump < 2'b10) begin
						_sv2v_jump = 2'b00;
						if (~mc[23]) begin
							if (mc != 0) begin
								mc = mc << 1;
								ec = ec - 1;
								if (mc[23])
									_sv2v_jump = 2'b10;
							end
							else
								mc = mc;
						end
						_sv2v_value_on_break = l;
					end
				if (!(_sv2v_jump < 2'b10))
					l = _sv2v_value_on_break;
				if (_sv2v_jump != 2'b11)
					_sv2v_jump = 2'b00;
			end
		end
	end
endmodule

Design/ks_vandana_fp_div_tb.v
module ks_vandana_fp_div_tb();
reg [31:0]a1,b1;
reg clk;
wire [31:0]c1;

ks_vandana_fp_div DUT(a1,b1,c1,clk);
initial begin
$dumpfile("ks_vandana_fp_div.vcd");
$dumpvars(0,ks_vandana_fp_div_tb);
end
initial clk=0;
always #5 clk=~clk;
initial begin
a1=32'b01000010111101111011001100110011;//123.85
b1=32'b01000010001101100000000000000000;//45.5
//123.85/45.5 = 2.721978022
#50
a1=32'b01000010000101110101000011100101;//37.829
b1=32'b01000000000010001110010101100000;//2.139
//37.829/2.139 = 17.68536699
#50
a1=32'b01000010100001101101001101110101;//67.413
b1=32'b01000001000011110001001001101111;//8.942
//67.413/8.942 = 7.538917468
#250 $finish;
end
endmodule

STAGE_1/ks_vandana_fp_div.vcd
$date
	Thu Oct 19 14:44:10 2023
$end
$version
	Icarus Verilog
$end
$timescale
	1s
$end
$scope module ks_vandana_fp_div_tb $end
$var wire 32 ! c1 [31:0] $end
$var reg 32 " a1 [31:0] $end
$var reg 32 # b1 [31:0] $end
$var reg 1 $ clk $end
$scope module DUT $end
$var wire 32 % a1 [31:0] $end
$var wire 32 & b1 [31:0] $end
$var wire 1 $ clk $end
$var reg 32 ' a [31:0] $end
$var reg 32 ( b [31:0] $end
$var reg 32 ) c [31:0] $end
$var reg 8 * ea [7:0] $end
$var reg 8 + eb [7:0] $end
$var reg 8 , ec [7:0] $end
$var reg 24 - ma [23:0] $end
$var reg 24 . mb [23:0] $end
$var reg 24 / mc [23:0] $end
$var reg 50 0 rq [49:0] $end
$var reg 1 1 sa $end
$var reg 1 2 sb $end
$var reg 1 3 sc $end
$scope begin sv2v_autoblock_1 $end
$var reg 2 4 _sv2v_jump [0:1] $end
$scope begin sv2v_autoblock_2 $end
$var reg 32 5 t [31:0] $end
$upscope $end
$scope begin sv2v_autoblock_3 $end
$var reg 32 6 l [31:0] $end
$scope begin sv2v_autoblock_4 $end
$var reg 32 7 _sv2v_value_on_break [31:0] $end
$upscope $end
$upscope $end
$upscope $end
$upscope $end
$upscope $end
$enddefinitions $end
#0
$dumpvars
bx 7
bx 6
bx 5
bx 4
x3
x2
x1
bx 0
bx /
bx .
bx -
bx ,
bx +
bx *
bx )
bx (
bx '
b1000010001101100000000000000000 &
b1000010111101111011001100110011 %
0$
b1000010001101100000000000000000 #
b1000010111101111011001100110011 "
bx !
$end
#5
b11000 7
b11001 6
b11000 5
b111100000000000000000101011100011010011100011 0
b101011100011010011100011 /
b101101100000000000000000 .
b111101111011001100110011 -
b10000000 ,
b10000100 +
b10000101 *
03
02
01
b0 4
b1000010001101100000000000000000 (
b1000010111101111011001100110011 '
1$
#10
0$
#15
b1000000001011100011010011100011 !
b1000000001011100011010011100011 )
1$
#20
0$
#25
1$
#30
0$
#35
1$
#40
0$
#45
1$
#50
0$
b1000000000010001110010101100000 #
b1000000000010001110010101100000 &
b1000010000101110101000011100101 "
b1000010000101110101000011100101 %
#55
b11000 7
b11001 6
b11000 5
b10100101001111010100000100011010111101110100001 0
b100011010111101110100001 /
b100010001110010101100000 .
b100101110101000011100101 -
b10000011 ,
b10000000 +
b10000100 *
b1000000000010001110010101100000 (
b1000010000101110101000011100101 '
1$
#60
0$
#65
b1000001100011010111101110100001 !
b1000001100011010111101110100001 )
1$
#70
0$
#75
1$
#80
0$
#85
1$
#90
0$
#95
1$
#100
0$
b1000001000011110001001001101111 #
b1000001000011110001001001101111 &
b1000010100001101101001101110101 "
b1000010100001101101001101110101 %
#105
b0 7
b0 4
b0 6
b11000 5
b11101001010010001010111011110001001111101100111 0
b111100010011111011001110 /
b100011110001001001101111 .
b100001101101001101110101 -
b10000001 ,
b10000010 +
b10000101 *
b1000001000011110001001001101111 (
b1000010100001101101001101110101 '
1$
#110
0$
#115
b1000000111100010011111011001110 !
b1000000111100010011111011001110 )
1$
